setup.py
trggr.py
trggrclear.py
trggrinit.py
trggr.egg-info/PKG-INFO
trggr.egg-info/SOURCES.txt
trggr.egg-info/dependency_links.txt
trggr.egg-info/top_level.txt