Metadata-Version: 1.0
Name: trggr
Version: 0.8
Summary: Execute a command from a namedpipe
Home-page: https://bitbucket.org/rit/trggr
Author: Rit Li
Author-email: rit@quietdynamite.com
License: MIT
Keywords: automation tool editor
Platform: UNKNOWN
